django_bootstrap_base_template/__init__.py
django_bootstrap_base_template/settings.py
django_bootstrap_base_template/urls.py
django_bootstrap_base_template/wsgi.py
django_bootstrap_base_template/static/css/bootstrap-grid.css
django_bootstrap_base_template/static/css/bootstrap-grid.min.css
django_bootstrap_base_template/static/css/bootstrap-reboot.css
django_bootstrap_base_template/static/css/bootstrap-reboot.min.css
django_bootstrap_base_template/static/css/bootstrap.css
django_bootstrap_base_template/static/css/bootstrap.min.css
django_bootstrap_base_template/static/css/font-awesome.min.css
django_bootstrap_base_template/static/fonts/FontAwesome.otf
django_bootstrap_base_template/static/fonts/fontawesome-webfont.eot
django_bootstrap_base_template/static/fonts/fontawesome-webfont.svg
django_bootstrap_base_template/static/fonts/fontawesome-webfont.ttf
django_bootstrap_base_template/static/fonts/fontawesome-webfont.woff
django_bootstrap_base_template/static/fonts/fontawesome-webfont.woff2
django_bootstrap_base_template/static/js/bootstrap.js
django_bootstrap_base_template/static/js/bootstrap.min.js
django_bootstrap_base_template/static/js/csrf.js
django_bootstrap_base_template/static/js/jquery.min.js
django_bootstrap_base_template/static/js/js.cookie.js
django_bootstrap_base_template/static/js/popper.min.js
django_bootstrap_base_template/templates/bootstrap_base.html
django_bootstrap_base_template-0.0.2.dist-info/DESCRIPTION.rst
django_bootstrap_base_template-0.0.2.dist-info/METADATA
django_bootstrap_base_template-0.0.2.dist-info/RECORD
django_bootstrap_base_template-0.0.2.dist-info/WHEEL
django_bootstrap_base_template-0.0.2.dist-info/metadata.json
django_bootstrap_base_template-0.0.2.dist-info/top_level.txt
django_bootstrap_base_template-0.0.2.dist-info/zip-safe
