Metadata-Version: 2.0
Name: django-bootstrap-base-template
Version: 0.0.2
Summary: 
